jito_py_rpc/__init__.py
jito_py_rpc/jito_jsonrpc_sdk.py
jito_py_rpc-0.1.5.dist-info/licenses/LICENSE
jito_py_rpc-0.1.5.dist-info/METADATA
jito_py_rpc-0.1.5.dist-info/WHEEL
jito_py_rpc-0.1.5.dist-info/top_level.txt
jito_py_rpc-0.1.5.dist-info/RECORD
